quirtylog/__init__.py
quirtylog/__main__.py
quirtylog/core.py
quirtylog/logging.yaml
quirtylog/sqlite_logger.py
quirtylog/tqdm_logger.py
quirtylog-0.7.0.dist-info/licenses/LICENSE
quirtylog-0.7.0.dist-info/METADATA
quirtylog-0.7.0.dist-info/WHEEL
quirtylog-0.7.0.dist-info/top_level.txt
quirtylog-0.7.0.dist-info/RECORD
