Metadata-Version: 2.4
Name: quirtylog
Version: 0.7.0
Author-email: agdiiura <andreadiiura@gmail.com>
Project-URL: Homepage, https://github.com/agdiiura/quirtylog
Project-URL: Documentation, https://quirtylog.readthedocs.io/en/stable/index.html
Project-URL: Repository, https://github.com/agdiiura/quirtylog.git
License-File: LICENSE
Requires-Dist: coloredlogs>=10.0
Requires-Dist: joblib>=1.3.2
Requires-Dist: PyYAML>=6.0.1
Requires-Dist: tqdm>=4.66.1
Provides-Extra: build
Requires-Dist: ruff>=0.14.0; extra == "build"
Requires-Dist: colorama>=0.4.6; extra == "build"
Requires-Dist: coverage>=7.0; extra == "build"
Requires-Dist: isort>=6.0.0; extra == "build"
Requires-Dist: pre-commit>=4.0.0; extra == "build"
Requires-Dist: setuptools-git-versioning>=1.13.4; extra == "build"
Requires-Dist: unittest-xml-reporting>=3.2.0; extra == "build"
Requires-Dist: pandas>=2.2.0; extra == "build"
Provides-Extra: docs
Requires-Dist: GitPython>=3.1.3; extra == "docs"
Requires-Dist: recommonmark>=0.5.0; extra == "docs"
Requires-Dist: requests>=2.23.0; extra == "docs"
Requires-Dist: Sphinx==8.2.3; extra == "docs"
Requires-Dist: sphinx-autodoc-typehints>=1.20.0; extra == "docs"
Requires-Dist: sphinx-rtd-theme>=2.0.0; extra == "docs"
Dynamic: license-file
